{
  "databaseChangeLog": [
    {
      "preConditions": [
        {
          "not": {
            "tableExists": {
              "tableName": "user_categories"
            }
          }
        }
      ],
      "changeSet": {
        "id": "SP1 - create table user_categories",
        "author": "juan-para",
        "comment": "create table user_categories",
        "changes": [
          {
            "createTable": {
              "tableName": "user_categories",
              "columns": [
                {
                  "column": {
                    "name": "user_category_id",
                    "type": "INT",
                    "autoIncrement": true,
                    "constraints": {
                      "primaryKey": true,
                      "nullable": false
                    }
                  }
                },
                {
                  "column": {
                    "name": "category_name",
                    "type": "VARCHAR(100)",
                    "constraints": {
                      "nullable": false
                    }
                  }
                },
                {
                  "column": {
                    "name": "category_description",
                    "type": "VARCHAR(255)",
                    "constraints": {
                      "nullable": false
                    }
                  }
                }
              ]
            }
          }
        ]
      }
    }
  ]
}


